filmsdk_ibrahim/__init__.py
filmsdk_ibrahim/film_client.py
filmsdk_ibrahim/film_config.py
filmsdk_ibrahim/schemas/__init__.py
filmsdk_ibrahim/schemas/schemas.py
filmsdk_ibrahim-0.0.4.dist-info/METADATA
filmsdk_ibrahim-0.0.4.dist-info/WHEEL
filmsdk_ibrahim-0.0.4.dist-info/top_level.txt
filmsdk_ibrahim-0.0.4.dist-info/RECORD
